[
	{
		"__TYPE__": "SharedSliceContent",
		"variation": "default",
		"primary": {
			"description": {
				"__TYPE__": "StructuredTextContent",
				"value": [
					{
						"type": "paragraph",
						"content": {
							"text": "Discover the Best of Italy, from the ancient treasures of Rome to Renaissance Florence and everything in between. Imagine staying overnight in a renovated Franciscan monastery in Assisi, lapping up the chic lifestyle on Capri, and taking a private guided visit to Pompeii to see a Roman city frozen in time.",
							"spans": []
						},
						"direction": "ltr"
					}
				]
			},
			"details": {
				"__TYPE__": "GroupContentType",
				"value": [
					{
						"__TYPE__": "GroupItemContent",
						"value": [
							[
								"icon",
								{
									"origin": {
										"id": "main",
										"url": "https://images.unsplash.com/photo-1607582278038-6bebbd4d7b72",
										"width": 4010,
										"height": 4010
									},
									"url": "https://images.unsplash.com/photo-1607582278038-6bebbd4d7b72",
									"width": 4010,
									"height": 4010,
									"edit": {
										"zoom": 1,
										"crop": {
											"x": 0,
											"y": 0
										},
										"background": "transparent"
									},
									"credits": null,
									"alt": "chemical",
									"__TYPE__": "ImageContent",
									"thumbnails": {}
								}
							],
							[
								"title",
								{
									"__TYPE__": "FieldContent",
									"type": "Text",
									"value": "Travel"
								}
							],
							[
								"description",
								{
									"__TYPE__": "FieldContent",
									"type": "Text",
									"value": "13 days, 2 countries and 15 cities"
								}
							]
						]
					},
					{
						"__TYPE__": "GroupItemContent",
						"value": [
							[
								"title",
								{
									"__TYPE__": "FieldContent",
									"type": "Text",
									"value": "Acommodation"
								}
							],
							[
								"description",
								{
									"__TYPE__": "FieldContent",
									"type": "Text",
									"value": "12 nights"
								}
							],
							[
								"icon",
								{
									"provider": "imgix",
									"url": "https://images.unsplash.com/photo-1597588942474-cf4994da7575?crop=entropy&cs=srgb&fm=jpg&ixid=M3wzMzc0NjN8MHwxfHNlYXJjaHwxMnx8Y2l0cnVzJTIwZnJ1aXR8ZW58MHx8fHwxNzI0MTA2NTE3fDA&ixlib=rb-4.0.3&q=85",
									"alt": "yellow lemon fruit on brown wooden table",
									"origin": {
										"id": "vCYeEUYGSKw",
										"url": "https://images.unsplash.com/photo-1597588942474-cf4994da7575?crop=entropy&cs=srgb&fm=jpg&ixid=M3wzMzc0NjN8MHwxfHNlYXJjaHwxMnx8Y2l0cnVzJTIwZnJ1aXR8ZW58MHx8fHwxNzI0MTA2NTE3fDA&ixlib=rb-4.0.3&q=85",
										"width": 4032,
										"height": 3024
									},
									"width": 4032,
									"height": 3024,
									"edit": {
										"background": "transparent",
										"zoom": 1,
										"crop": {
											"x": 0,
											"y": 0
										}
									},
									"credits": null,
									"__TYPE__": "ImageContent",
									"thumbnails": {}
								}
							]
						]
					},
					{
						"__TYPE__": "GroupItemContent",
						"value": [
							[
								"title",
								{
									"__TYPE__": "FieldContent",
									"type": "Text",
									"value": "Meals"
								}
							],
							[
								"description",
								{
									"__TYPE__": "FieldContent",
									"type": "Text",
									"value": "12 Breakfasts, 6 Dinners"
								}
							],
							[
								"icon",
								{
									"provider": "imgix",
									"url": "https://images.unsplash.com/photo-1592951271867-b4e76e837658?crop=entropy&cs=srgb&fm=jpg&ixid=M3wzMzc0NjN8MHwxfHNlYXJjaHw5fHxjaXRydXMlMjBmcnVpdHxlbnwwfHx8fDE3MjQxMDY1MTd8MA&ixlib=rb-4.0.3&q=85",
									"alt": "yellow lemon fruit on white surface",
									"origin": {
										"id": "pocwmEqrW0g",
										"url": "https://images.unsplash.com/photo-1592951271867-b4e76e837658?crop=entropy&cs=srgb&fm=jpg&ixid=M3wzMzc0NjN8MHwxfHNlYXJjaHw5fHxjaXRydXMlMjBmcnVpdHxlbnwwfHx8fDE3MjQxMDY1MTd8MA&ixlib=rb-4.0.3&q=85",
										"width": 3024,
										"height": 3024
									},
									"width": 3024,
									"height": 3024,
									"edit": {
										"background": "transparent",
										"zoom": 1,
										"crop": {
											"x": 0,
											"y": 0
										}
									},
									"credits": null,
									"__TYPE__": "ImageContent",
									"thumbnails": {}
								}
							]
						]
					},
					{
						"__TYPE__": "GroupItemContent",
						"value": [
							[
								"description",
								{
									"__TYPE__": "FieldContent",
									"type": "Text",
									"value": "View day-by-day trip itinerary"
								}
							],
							[
								"title",
								{
									"__TYPE__": "FieldContent",
									"type": "Text",
									"value": "Itinerary"
								}
							],
							[
								"icon",
								{
									"provider": "imgix",
									"url": "https://images.unsplash.com/photo-1629122998682-9f01c0fa89ed?crop=entropy&cs=srgb&fm=jpg&ixid=M3wzMzc0NjN8MHwxfHNlYXJjaHw4fHxjaXRydXMlMjBmcnVpdHxlbnwwfHx8fDE3MjQxMDY1MTd8MA&ixlib=rb-4.0.3&q=85",
									"alt": "orange fruits on green leaves",
									"origin": {
										"id": "_ANDM3OI4gE",
										"url": "https://images.unsplash.com/photo-1629122998682-9f01c0fa89ed?crop=entropy&cs=srgb&fm=jpg&ixid=M3wzMzc0NjN8MHwxfHNlYXJjaHw4fHxjaXRydXMlMjBmcnVpdHxlbnwwfHx8fDE3MjQxMDY1MTd8MA&ixlib=rb-4.0.3&q=85",
										"width": 3024,
										"height": 4032
									},
									"width": 3024,
									"height": 4032,
									"edit": {
										"background": "transparent",
										"zoom": 1,
										"crop": {
											"x": 0,
											"y": 0
										}
									},
									"credits": null,
									"__TYPE__": "ImageContent",
									"thumbnails": {}
								}
							]
						]
					}
				]
			},
			"tour_image": {
				"origin": {
					"id": "main",
					"url": "https://images.unsplash.com/photo-1587613865763-4b8b0d19e8ab",
					"width": 12288,
					"height": 16384
				},
				"url": "https://images.unsplash.com/photo-1587613865763-4b8b0d19e8ab",
				"width": 12288,
				"height": 16384,
				"edit": {
					"zoom": 1,
					"crop": {
						"x": 0,
						"y": 0
					},
					"background": "transparent"
				},
				"credits": null,
				"alt": "tour",
				"__TYPE__": "ImageContent",
				"thumbnails": {}
			},
			"title": {
				"__TYPE__": "StructuredTextContent",
				"value": [
					{
						"type": "heading2",
						"content": {
							"text": "13-Day Italy Sightseeing Tour of Rome, Lake Como and Sorrento",
							"spans": []
						},
						"direction": "ltr"
					}
				]
			},
			"booking_info_title": {
				"__TYPE__": "StructuredTextContent",
				"value": [
					{
						"type": "heading2",
						"content": {
							"text": "Looking to book in a group of 15 or more?",
							"spans": []
						},
						"direction": "ltr"
					}
				]
			},
			"booking_info_description": {
				"__TYPE__": "StructuredTextContent",
				"value": [
					{
						"type": "paragraph",
						"content": {
							"text": "Deals, savings and exclusive private touring options available plus if you need a different date or itinerary change we can create a custom trip. Contact us for more details",
							"spans": []
						},
						"direction": "ltr"
					}
				]
			},
			"trip_code_text": {
				"__TYPE__": "FieldContent",
				"type": "Text",
				"value": "Trip Code"
			},
			"trip_code_value": {
				"__TYPE__": "FieldContent",
				"type": "Text",
				"value": "ITOB"
			}
		},
		"items": []
	}
]